permchain/__init__.py
permchain/channels/__init__.py
permchain/channels/base.py
permchain/channels/binop.py
permchain/channels/context.py
permchain/channels/last_value.py
permchain/channels/topic.py
permchain/checkpoint/__init__.py
permchain/checkpoint/base.py
permchain/checkpoint/memory.py
permchain/constants.py
permchain/pregel/__init__.py
permchain/pregel/debug.py
permchain/pregel/io.py
permchain/pregel/log.py
permchain/pregel/read.py
permchain/pregel/reserved.py
permchain/pregel/validate.py
permchain/pregel/write.py
permchain/utils.py
permchain-0.0.7.dist-info/LICENSE
permchain-0.0.7.dist-info/METADATA
permchain-0.0.7.dist-info/WHEEL
permchain-0.0.7.dist-info/RECORD
