Metadata-Version: 2.1
Name: permchain
Version: 0.0.7
Summary: permchain
Home-page: https://www.github.com/langchain-ai/permchain
License: MIT
Requires-Python: >=3.8.1,<4.0
Classifier: License :: OSI Approved :: MIT License
Classifier: Programming Language :: Python :: 3
Classifier: Programming Language :: Python :: 3.9
Classifier: Programming Language :: Python :: 3.10
Classifier: Programming Language :: Python :: 3.11
Requires-Dist: langchain (>=0.0.335)
Project-URL: Repository, https://www.github.com/langchain-ai/permchain
